streamlit_monaco/__init__.py
streamlit_monaco/flags.py
streamlit_monaco/render.py
streamlit_monaco/frontend/build/404.html
streamlit_monaco/frontend/build/index.html
streamlit_monaco/frontend/build/_next/static/0_bpMIJfqlKNl0llWceeZ/_buildManifest.js
streamlit_monaco/frontend/build/_next/static/0_bpMIJfqlKNl0llWceeZ/_ssgManifest.js
streamlit_monaco/frontend/build/_next/static/Cu9CZCMYgS1XsYxJlPkz4/_buildManifest.js
streamlit_monaco/frontend/build/_next/static/Cu9CZCMYgS1XsYxJlPkz4/_ssgManifest.js
streamlit_monaco/frontend/build/_next/static/WqqnjnSpk1nIl-KmIQ-P8/_buildManifest.js
streamlit_monaco/frontend/build/_next/static/WqqnjnSpk1nIl-KmIQ-P8/_ssgManifest.js
streamlit_monaco/frontend/build/_next/static/chunks/583.6eb60e0e19a36bdd.js
streamlit_monaco/frontend/build/_next/static/chunks/87.7869b76f084ccd7a.js
streamlit_monaco/frontend/build/_next/static/chunks/87.ee7c8213e1436687.js
streamlit_monaco/frontend/build/_next/static/chunks/framework-f818b5a5e39b2c1d.js
streamlit_monaco/frontend/build/_next/static/chunks/main-12e9c77dbbe57e7c.js
streamlit_monaco/frontend/build/_next/static/chunks/polyfills-c67a75d1b6f99dc8.js
streamlit_monaco/frontend/build/_next/static/chunks/webpack-1af6694ef63ad82e.js
streamlit_monaco/frontend/build/_next/static/chunks/webpack-835a116dc03060b4.js
streamlit_monaco/frontend/build/_next/static/chunks/pages/_app-17d19c65739e24e7.js
streamlit_monaco/frontend/build/_next/static/chunks/pages/_error-8b31ab893441781f.js
streamlit_monaco/frontend/build/_next/static/chunks/pages/index-bccd7a6c9389b5db.js
streamlit_monaco/frontend/build/_next/static/iBFH_u2WmnvOCEH4vmVZG/_buildManifest.js
streamlit_monaco/frontend/build/_next/static/iBFH_u2WmnvOCEH4vmVZG/_ssgManifest.js
streamlit_monaco/frontend/build/_next/static/p2KBUHUbJdAQ6fTVns5-8/_buildManifest.js
streamlit_monaco/frontend/build/_next/static/p2KBUHUbJdAQ6fTVns5-8/_ssgManifest.js
streamlit_monaco/frontend/build/_next/static/shnUQEP9Uhlt6kATKgn74/_buildManifest.js
streamlit_monaco-0.1.3.dist-info/LICENSE
streamlit_monaco-0.1.3.dist-info/METADATA
streamlit_monaco-0.1.3.dist-info/WHEEL
streamlit_monaco-0.1.3.dist-info/top_level.txt
streamlit_monaco-0.1.3.dist-info/RECORD
