Metadata-Version: 2.1
Name: streamlit-monaco
Version: 0.1.3
Summary: Monaco Editor (Visual Studio Code) for Streamlit
Home-page: https://github.com/marcusschiesser/streamlit-monaco
Author: marcusschiesser
License: MIT
Requires-Python: >=3.9
License-File: LICENSE
